easyRTML/__init__.py
easyRTML/auth.py
easyRTML/check.py
easyRTML/credentials.encrypted
easyRTML/dataaq.py
easyRTML/encryption.py
easyRTML/extract.py
easyRTML/pipe.py
easyRTML/plot.py
easyRTML/process.py
easyRTML/pyRTML.py
easyRTML/rb.py
easyRTML/secret.key
easyRTML/xg.py
easyRTML/xg_port.py
easyRTML-1.6.6.dist-info/LICENSE
easyRTML-1.6.6.dist-info/METADATA
easyRTML-1.6.6.dist-info/WHEEL
easyRTML-1.6.6.dist-info/top_level.txt
easyRTML-1.6.6.dist-info/RECORD
