Metadata-Version: 2.1
Name: easyRTML
Version: 1.6.6
Summary: A package for signal classification and deployment in any microcontroller board with no expertise required.
Home-page: https://github.com/easyRTML
Author: Aryan Jadhav
Author-email: easiestrtml@gmail.com
License: MIT
Platform: UNKNOWN
Classifier: Programming Language :: Python :: 3
Classifier: License :: OSI Approved :: MIT License
Classifier: Operating System :: OS Independent
Requires-Python: >=3.6
License-File: LICENSE
Requires-Dist: pandas
Requires-Dist: numpy
Requires-Dist: xgboost
Requires-Dist: scikit-learn
Requires-Dist: matplotlib
Requires-Dist: seaborn
Requires-Dist: tqdm
Requires-Dist: pyserial
Requires-Dist: gspread
Requires-Dist: google-auth
